arrpc/__init__.py
arrpc/client.py
arrpc/error.py
arrpc/metrics.py
arrpc/server.py
arrpc/utils.py
arrpc/version.py
arrpc-0.5.0.dist-info/LICENSE
arrpc-0.5.0.dist-info/METADATA
arrpc-0.5.0.dist-info/WHEEL
arrpc-0.5.0.dist-info/top_level.txt
arrpc-0.5.0.dist-info/RECORD
