Metadata-Version: 2.1
Name: arrpc
Version: 0.5.0
Summary: Simple, speedy and light Python3 RPC
Home-page: https://github.com/adrianchifor/arrpc
Author: Adrian Chifor
Author-email: me@adrianchifor.com
License: Apache License 2.0
Keywords: rpc msgpack gevent
Platform: UNKNOWN
Classifier: Development Status :: 4 - Beta
Classifier: Intended Audience :: Developers
Classifier: Topic :: Software Development :: Libraries :: Python Modules
Classifier: Topic :: System :: Distributed Computing
Classifier: License :: OSI Approved :: Apache Software License
Classifier: Programming Language :: Python :: 3.6
Classifier: Programming Language :: Python :: 3.7
Requires-Python: >=3.6
License-File: LICENSE
Requires-Dist: msgpack (>=1.0.3)
Requires-Dist: gevent (>=21.12.0)
Requires-Dist: prometheus-client (>=0.13.1)
